hypothesis_gentoo.py
hypothesis_gentoo-4.dist-info/entry_points.txt
hypothesis_gentoo-4.dist-info/licenses/LICENSE
hypothesis_gentoo-4.dist-info/WHEEL
hypothesis_gentoo-4.dist-info/METADATA
hypothesis_gentoo-4.dist-info/RECORD
