Metadata-Version: 2.4
Name: hypothesis_gentoo
Version: 4
Summary: Plugin to create "gentoo" hypothesis profile, disabling health checks
Author-email: Michał Górny <mgorny@gentoo.org>
License-Expression: MIT
License-File: LICENSE
Project-URL: Home, https://github.com/projg2/hypothesis_gentoo/
